final_test03/__init__.py
final_test03/adaboost.py
final_test03/grad_boost.py
final_test03/knn.py
final_test03/logistic.py
final_test03/mlp.py
final_test03/perceptron.py
final_test03/random_forest.py
final_test03/sgd.py
final_test03/support_vector.py
final_test03/visualize.py
final_test03/xgboost.py
final_test_03-0.1.0.dist-info/LICENSE
final_test_03-0.1.0.dist-info/METADATA
final_test_03-0.1.0.dist-info/WHEEL
final_test_03-0.1.0.dist-info/top_level.txt
final_test_03-0.1.0.dist-info/RECORD
